git_revise-0.7.0.data/data/share/man/man1/git-revise.1
gitrevise/__init__.py
gitrevise/__main__.py
gitrevise/merge.py
gitrevise/odb.py
gitrevise/todo.py
gitrevise/tui.py
gitrevise/utils.py
git_revise-0.7.0.dist-info/LICENSE
git_revise-0.7.0.dist-info/METADATA
git_revise-0.7.0.dist-info/WHEEL
git_revise-0.7.0.dist-info/entry_points.txt
git_revise-0.7.0.dist-info/top_level.txt
git_revise-0.7.0.dist-info/RECORD
