Metadata-Version: 2.1
Name: git-revise
Version: 0.7.0
Summary: Efficiently update, split, and rearrange git commits
Home-page: https://github.com/mystor/git-revise
Author: Nika Layzell
Author-email: nika@thelayzells.com
License: MIT
Project-URL: Bug Tracker, https://github.com/mystor/git-revise/issues/
Project-URL: Source Code, https://github.com/mystor/git-revise/
Project-URL: Documentation, https://git-revise.readthedocs.io/en/latest/
Keywords: git revise rebase amend fixup
Platform: UNKNOWN
Classifier: Development Status :: 4 - Beta
Classifier: Intended Audience :: Developers
Classifier: Environment :: Console
Classifier: Topic :: Software Development :: Version Control
Classifier: Topic :: Software Development :: Version Control :: Git
Classifier: License :: OSI Approved :: MIT License
Classifier: Programming Language :: Python :: 3
Classifier: Programming Language :: Python :: 3.8
Classifier: Programming Language :: Python :: 3.9
Classifier: Programming Language :: Python :: 3.10
Requires-Python: >=3.8
